Workbook

Sheet Inputs
A1: Переменная | B1: Значение | C1: Единица | D1: Источник/как получить | E1: Комментарий
A2: usd_rub | C2: RUB/USD | D2: Курс для planning | E2: Заполняется вручную
A3: reve_purchase_usd | B3: 10 | C3: USD | D3: Reve console | E3: Минимальная покупка credits
A4: reve_purchase_credits | B4: 7500 | C4: credits | D4: Reve console | E4: Credits за $10
A5: reve_credit_usd | B5: =B3/B4 | C5: USD/credit | D5: Formula | E5: Цена одного Reve credit
A6: b2c_fast_share | B6: 0.7 | C6: % | D6: Planning hypothesis | E6: Доля Remix Fast в B2C
A7: b2c_standard_share | B7: 0.3 | C7: % | D7: Planning hypothesis | E7: Доля Remix в B2C
A8: b2c_fallback_share | B8: 0 | C8: % | D8: Planning hypothesis | E8: Доля premium fallback
A9: fallback_attempt_usd | C9: USD | D9: Provider docs/billing | E9: OpenAI или другой fallback
A10: api_cost_attempt_avg_usd | B10: =B6*Reve11!D3+B7*Reve11!D4+B8*B9 | C10: USD | D10: Formula | E10: Средняя цена B2C попытки
A11: api_cost_attempt_avg_rub | B11: =B10*B2 | C11: RUB | D11: Formula | E11: Средняя цена B2C попытки
A12: attempts_per_success | C12: x | D12: 30-50 test pairs / production usage | E12: Среднее число попыток на successful render
A13: technical_failure_rate | C13: % | D13: failed / total_jobs | E13: Технические jobs без результата
A14: payment_fee_rate | C14: % | D14: Robokassa contract/dashboard | E14: Процент комиссии
A15: payment_fee_fixed | C15: RUB | D15: Robokassa contract/dashboard | E15: Фиксированная комиссия
A16: infra_monthly | C16: RUB/month | D16: Render/Supabase/Redis/Storage | E16: Месячная инфраструктура
A17: paid_renders_month | C17: renders | D17: Sales plan / actual usage | E17: Платные successful renders
A18: support_buffer_render | C18: RUB | D18: Support estimate | E18: Буфер на поддержку/споры
A19: free_trial_renders | C19: renders | D19: Free trial cap | E19: Лимит бесплатных renders
A20: refund_rate | C20: % | D20: Payment/refund events | E20: Доля оплат с возвратом
A21: target_margin_founder | C21: RUB | D21: Business decision | E21: Желаемая маржа с Founder Pass
A22: internal_credit_cost_rub | C22: RUB | D22: Business decision | E22: Для B2B2C dynamic credit spend

Sheet Reve11
A1: Pipeline | B1: Credits used | C1: Formula USD | D1: USD / attempt | E1: B2C role
A2: Create | B2: 18 | C2: =B2*Inputs!B5 | D2: =C2 | E2: not primary
A3: Remix Fast | B3: 5 | C3: =B3*Inputs!B5 | D3: =C3 | E3: cheap B2C baseline
A4: Remix | B4: 30 | C4: =B4*Inputs!B5 | D4: =C4 | E4: quality B2C baseline
A5: Edit Fast | B5: 5 | C5: =B5*Inputs!B5 | D5: =C5 | E5: possible mask/edit step
A6: Edit | B6: 30 | C6: =B6*Inputs!B5 | D6: =C6 | E6: possible quality edit step

Sheet Calculator
A1: Метрика | B1: Формула/значение | C1: Комментарий
A2: api_cost_success_rub | B2: =Inputs!B11*Inputs!B12 | C2: Средняя API себестоимость successful render
A3: infra_cost_per_render | B3: =Inputs!B16/MAX(Inputs!B17,1) | C3: Инфраструктура на платный render
A4: cogs_per_success | B4: =B2+B3+Inputs!B18 | C4: Полная себестоимость successful render
A5: free_trial_budget | B5: =Inputs!B19*B4 | C5: Бюджет free trial
A6: founder_pass_price | B6: 500 | C6: Июньская предоплата
A7: founder_payment_fee | B7: =B6*Inputs!B14+Inputs!B15 | C7: Комиссия оплаты
A8: max_credits_for_founder_pass | B8: =ROUNDDOWN((B6-B7-Inputs!B21)/MAX(B4,0.01),0) | C8: Hard cap по credits

Sheet Packages
A1: Package | B1: Role | C1: Price RUB | D1: Credits | E1: Payment fee | F1: Package COGS | G1: Contribution margin | H1: Margin % | I1: Launch condition
A2: Free Trial | B2: Magic moment | C2: 0 | D2: 1 | E2: =C2*Inputs!B14+Inputs!B15 | F2: =D2*Calculator!B4 | G2: =C2-E2-F2 | H2: =IF(C2=0,"n/a",G2/C2) | I2: Only with monthly budget cap
A3: Start | B3: First paid step | E3: =C3*Inputs!B14+Inputs!B15 | F3: =D3*Calculator!B4 | G3: =C3-E3-F3 | H3: =IF(C3=0,"",G3/C3) | I3: Positive margin required
A4: Founder Pass | B4: June preorder | C4: 500 | D4: =Calculator!B8 | E4: =C4*Inputs!B14+Inputs!B15 | F4: =D4*Calculator!B4 | G4: =C4-E4-F4 | H4: =IF(C4=0,"",G4/C4) | I4: Only with enforceable hard cap
A5: Pro | B5: Active shoppers | E5: =C5*Inputs!B14+Inputs!B15 | F5: =D5*Calculator!B4 | G5: =C5-E5-F5 | H5: =IF(C5=0,"",G5/C5) | I5: Not below COGS
A6: Master | B6: Later | E6: =C6*Inputs!B14+Inputs!B15 | F6: =D6*Calculator!B4 | G6: =C6-E6-F6 | H6: =IF(C6=0,"",G6/C6) | I6: Add after factual data

Sheet B2B2CPro
A1: Pipeline | B1: Components | C1: Provider cost formula USD | D1: Provider cost USD | E1: Credit spend formula | F1: Credit spend | G1: Use case
A2: Fast preview | B2: reve_remix_fast | C2: =Reve11!D3 | D2: =C2 | E2: =ROUNDUP(D2*Inputs!B2/MAX(Inputs!B22,0.01),0) | F2: =E2 | G2: fast catalog preview
A3: Standard fit | B3: reve_remix | C3: =Reve11!D4 | D3: =C3 | E3: =ROUNDUP(D3*Inputs!B2/MAX(Inputs!B22,0.01),0) | F3: =E3 | G3: default B2B2C quality
A4: Masked fit | B4: mask step + reve_remix | C4: =Reve11!D4+Reve11!D5 | D4: =C4 | E4: =ROUNDUP(D4*Inputs!B2/MAX(Inputs!B22,0.01),0) | F4: =E4 | G4: better body/wheel preservation
A5: Vehicle-aware | B5: vehicle detection + pipeline rules + reve_remix | C5: =Reve11!D4+0 | D5: =C5 | E5: =ROUNDUP(D5*Inputs!B2/MAX(Inputs!B22,0.01),0) | F5: =E5 | G5: fitment-aware storefront
A6: Premium fallback | B6: OpenAI/other provider | C6: =Inputs!B9 | D6: =C6 | E6: =ROUNDUP(D6*Inputs!B2/MAX(Inputs!B22,0.01),0) | F6: =E6 | G6: manual retry/high-value lead

Sheet MonthlyAverage
A1: Month | B1: Attempts | C1: Successful renders | D1: Provider cost USD | E1: USD/RUB | F1: Avg cost attempt USD | G1: Attempts/success | H1: Avg COGS success RUB
A2: 2026-06 | E2: =Inputs!B2 | F2: =IF(B2=0,"",D2/B2) | G2: =IF(C2=0,"",B2/C2) | H2: =IF(OR(F2="",G2=""),"",F2*G2*E2+Calculator!B3+Inputs!B18)

Sheet DataToCollect
A1: Данные | B1: Как получить | C1: Где хранить/событие | D1: Owner | E1: Status
A2: Фактическая цена Reve attempt | B2: credits_used * reve_credit_usd | C2: jobs.provider_cost_usd | D2: Backend | E2: Ready to log
A3: Pipeline mix | B3: count by pipeline_key | C3: jobs.pipeline_key | D3: Backend/Admin | E3: TBD
A4: Среднее attempts_per_success | B4: 30-50 реальных пар фото | C4: jobs.attempts_count | D4: ML/Product | E4: TBD
A5: Failure rate | B5: failed / total_jobs | C5: job_failed / job_created | D5: Backend | E5: TBD
A6: Среднее время генерации | B6: queued/processing/completed timestamps | C6: jobs timestamps | D6: Backend | E6: TBD
A7: Комиссия Robokassa | B7: Договор/кабинет Robokassa | C7: payment config | D7: Founder | E7: TBD
A8: Free trial conversion | B8: После первой недели запуска | C8: trial_used -> payment_paid | D8: Product | E8: TBD
A9: Конверсия upload -> successful render | B9: Аналитика Mini App | C9: job_completed / upload_started | D9: Frontend/Backend | E9: TBD
A10: Конверсия result -> checkout | B10: Аналитика Mini App | C10: checkout_opened / result_viewed | D10: Frontend | E10: TBD
A11: Конверсия checkout -> paid | B11: Backend payment events | C11: payment_paid / checkout_opened | D11: Backend | E11: TBD

Sheet AdminPanel
A1: Зона Admin Panel | B1: Что добавить | C1: Зачем
A2: Dashboard | B2: Revenue, paid preorders, active credits, trial usage, COGS estimate | C2: Контроль июньского плана
A3: Pipeline mix | B3: fast/standard/fallback share | C3: Динамический B2C average
A4: Provider costs | B4: provider_cost_usd, attempts_count | C4: Фактический cost_per_success
A5: Monthly snapshots | B5: monthly_unit_economics_snapshots | C5: Обновление цен раз в месяц
A6: Credits | B6: user balance + credit ledger | C6: Аудит начислений/списаний/refunds
A7: Jobs | B7: status, failure_reason, attempts_count, cost_estimate, credit_event_id | C7: Контроль качества и себестоимости
A8: Refunds | B8: manual refund/correction queue | C8: Спорные случаи и поддержка
A9: Receipts | B9: tax_receipt_status, receipt_url/manual note | C9: Не забыть чек

Sheet RefundFlow
A1: Событие | B1: Credit action | C1: Money action | D1: Техническое условие
A2: Job created | B2: Reserve 1 credit | C2: None | D2: DB transaction + idempotency key
A3: Job completed | B3: Finalize reserved credit | C3: None | D3: Only from processing/reserved state
A4: Technical failure | B4: Refund reserved credit automatically | C4: None by default | D4: Failure reason in technical whitelist
A5: Paid but unused package refund request | B5: Reverse unused credits/manual adjustment | C5: Robokassa/manual refund | D5: Support/admin review
A6: Bad subjective result | B6: No automatic refund | C6: Manual review only | D6: Quality complaint flag
